{
"type": "FeatureCollection",
"crs": { "type": "name", "properties": { "name": "urn:ogc:def:crs:OGC:1.3:CRS84" } },
"features": [
{ "type": "Feature", "properties": { "OBJECTID_1": 1, "OBJECTID": 29, "Name": "Rikheshowr gufa_8" }, "geometry": { "type": "Point", "coordinates": [ 85.174193875447031, 27.493481819930082, 0.0 ] } },
{ "type": "Feature", "properties": { "OBJECTID_1": 2, "OBJECTID": 26, "Name": "Rikheswor Gufa_7" }, "geometry": { "type": "Point", "coordinates": [ 85.119138033593458, 27.499342532631829, 0.0 ] } },
{ "type": "Feature", "properties": { "OBJECTID_1": 3, "OBJECTID": 4, "Name": "Rikheshwor Gufaa_5" }, "geometry": { "type": "Point", "coordinates": [ 85.15219170708167, 27.489528636737248, 0.0 ] } }
]
}
